[{"Id":2,"Name":"superuser","Password":"password","RefreshToken":null,"Groups":[{"Id":2,"Name":"superusers"},{"Id":3,"Name":"users"}]},{"Id":3,"Name":"john","Password":"password","RefreshToken":null,"Groups":[{"Id":3,"Name":"users"}]},{"Id":4,"Name":"jane","Password":"password","RefreshToken":null,"Groups":[{"Id":3,"Name":"users"}]},{"Id":1,"Name":"admin","Password":"password","RefreshToken":"8iKMuWNxqvZ/sukgeO1UnBfRUdCRu\u002BqmJAdVbGv7vBk=","Groups":[{"Id":1,"Name":"admins"},{"Id":2,"Name":"superusers"},{"Id":3,"Name":"users"}]}]